optflow/__init__.py
optflow/flow.py
optflow/util/__init__.py
optflow/util/util.py
optflow/viz/__init__.py
optflow/viz/display_flow.py
optflow/viz/visualize_state.py
optflow-0.0.1b1.dist-info/LICENSE
optflow-0.0.1b1.dist-info/METADATA
optflow-0.0.1b1.dist-info/WHEEL
optflow-0.0.1b1.dist-info/entry_points.txt
optflow-0.0.1b1.dist-info/top_level.txt
optflow-0.0.1b1.dist-info/RECORD
